<?xml version="1.0" encoding="utf-8"?>
<Animation name="newSpriteSheet.png" w="2048" h="2048">
  <dir name="FlyLeft">
    <spr name="270" x="1" y="3" w="20" h="32"/>
    <spr name="264" x="61" y="2" w="20" h="33"/>
    <spr name="258" x="120" y="2" w="20" h="33"/>
    <spr name="252" x="180" y="2" w="19" h="33"/>
    <spr name="246" x="240" y="2" w="19" h="33"/>
    <spr name="240" x="300" y="2" w="19" h="32"/>
    <spr name="234" x="359" y="2" w="21" h="32"/>
    <spr name="228" x="419" y="2" w="22" h="31"/>
    <spr name="222" x="479" y="2" w="23" h="30"/>
    <spr name="216" x="538" y="2" w="25" h="29"/>
    <spr name="210" x="598" y="3" w="26" h="28"/>
    <spr name="204" x="657" y="3" w="27" h="27"/>
    <spr name="198" x="717" y="4" w="28" h="24"/>
    <spr name="192" x="776" y="5" w="30" h="22"/>
    <spr name="186" x="836" y="5" w="30" h="21"/>
    <spr name="180" x="895" y="6" w="32" h="21"/>
    <spr name="174" x="955" y="7" w="32" h="20"/>
    <spr name="168" x="1014" y="8" w="33" h="21"/>
    <spr name="162" x="1074" y="9" w="33" h="19"/>
    <spr name="156" x="1134" y="9" w="33" h="19"/>
    <spr name="150" x="1194" y="10" w="33" h="18"/>
    <spr name="144" x="1254" y="9" w="32" h="19"/>
    <spr name="138" x="1314" y="8" w="32" h="21"/>
    <spr name="132" x="1374" y="7" w="31" h="22"/>
    <spr name="126" x="1432" y="5" w="34" h="25"/>
    <spr name="120" x="1493" y="5" w="34" h="25"/>
    <spr name="114" x="1552" y="4" w="34" h="27"/>
    <spr name="108" x="1610" y="3" w="34" h="29"/>
    <spr name="102" x="1676" y="3" w="24" h="28"/>
    <spr name="96" x="1737" y="2" w="22" h="30"/>
    <spr name="90" x="1798" y="2" w="20" h="31"/>
	
	
    <spr name="276" x="122" y="37" w="20" h="33"/>
    <spr name="282" x="183" y="37" w="19" h="33"/>
    <spr name="288" x="244" y="37" w="18" h="33"/>
    <spr name="294" x="303" y="37" w="19" h="32"/>
    <spr name="300" x="362" y="37" w="21" h="32"/>
    <spr name="306" x="421" y="37" w="22" h="31"/>
    <spr name="312" x="480" y="37" w="23" h="30"/>
    <spr name="318" x="539" y="37" w="25" h="29"/>
    <spr name="324" x="598" y="38" w="26" h="28"/>
    <spr name="330" x="658" y="38" w="27" h="27"/>
    <spr name="336" x="717" y="39" w="28" h="24"/>
    <spr name="342" x="776" y="40" w="30" h="22"/>
    <spr name="348" x="836" y="40" w="30" h="21"/>
    <spr name="354" x="895" y="41" w="32" h="21"/>
    <spr name="0" x="955" y="42" w="32" h="20"/>
	
    <spr name="6" x="1015" y="43" w="33" h="19"/>
    <spr name="12" x="1075" y="44" w="33" h="19"/>
    <spr name="18" x="1135" y="44" w="33" h="19"/>
    <spr name="24" x="1195" y="45" w="33" h="18"/>
    <spr name="30" x="1256" y="44" w="32" h="19"/>
    <spr name="36" x="1316" y="43" w="32" h="21"/>
    <spr name="42" x="1377" y="42" w="31" h="22"/>
    <spr name="48" x="1438" y="41" w="30" h="23"/>
    <spr name="54" x="1499" y="40" w="28" h="25"/>
    <spr name="60" x="1560" y="39" w="27" h="26"/>
    <spr name="66" x="1621" y="38" w="25" h="28"/>
    <spr name="72" x="1682" y="38" w="24" h="28"/>
    <spr name="78" x="1743" y="37" w="22" h="30"/>
    <spr name="84" x="1804" y="37" w="20" h="31"/>
	
	
  </dir>
</Animation>